Transkit/Api.py
Transkit/__init__.py
Transkit/test_Api.py
Transkit-1.0.0.dist-info/LICENSE
Transkit-1.0.0.dist-info/METADATA
Transkit-1.0.0.dist-info/WHEEL
Transkit-1.0.0.dist-info/top_level.txt
Transkit-1.0.0.dist-info/RECORD
