Metadata-Version: 2.1
Name: Transkit
Version: 1.0.0
Summary: Transkit API library
Home-page: https://github.com/Vicomtech/transkit-api-lib/
Author: Vicomtech
Author-email: posdig-dev@vicomtech.org
Classifier: Programming Language :: Python :: 3
Classifier: License :: OSI Approved :: GNU General Public License v3 (GPLv3)
Classifier: Operating System :: OS Independent
Requires-Python: >=3.6
License-File: LICENSE
